[
    {
        "code": "OK",
        "data": {
            "container": {
                "goods_id": 967941,
                "icon_url": "https://market.fp.ps.netease.com/file/66fde4d15e36956d6530882bVRKHVCzf05",
                "name": "\u753b\u5eca\u6b66\u5668\u7bb1",
                "sell_min_price": "4.7"
            },
            "has_unusual": true,
            "items": [
                {
                    "goods": {
                        "appid": 730,
                        "description": null,
                        "game": "csgo",
                        "goods_id": 968376,
                        "icon_url": "https://market.fp.ps.netease.com/file/66fe0af7765582cb9d9fa899Whwjh01605",
                        "is_charm": false,
                        "item_id": null,
                        "keychain_color_img": null,
                        "market_hash_name": "M4A1-S | Vaporwave (Factory New)",
                        "market_min_price": "0",
                        "name": "M4A1 \u6d88\u97f3\u578b | \u84b8\u6c7d\u6ce2 (\u5d2d\u65b0\u51fa\u5382)",
                        "original_icon_url": "https://market.fp.ps.netease.com/file/66fe0af4d69bd87634e6cc17isXJwY6z05",
                        "sell_min_price": "1538.35",
                        "sell_reference_price": "0",
                        "short_name": "M4A1 \u6d88\u97f3\u578b | \u84b8\u6c7d\u6ce2",
                        "steam_price": "264",
                        "steam_price_cny": "1909.84",
                        "tags": {
                            "category": {
                                "category": "category",
                                "id": 629,
                                "internal_name": "weapon_m4a1_silencer",
                                "localized_name": "M4A1 \u6d88\u97f3\u7248"
                            },
                            "category_group": {
                                "category": "category_group",
                                "id": 622,
                                "internal_name": "rifle",
                                "localized_name": "\u6b65\u67aa"
                            },
                            "exterior": {
                                "category": "exterior",
                                "id": 510,
                                "internal_name": "wearcategory0",
                                "localized_name": "\u5d2d\u65b0\u51fa\u5382"
                            },
                            "itemset": {
                                "category": "itemset",
                                "id": 19715,
                                "internal_name": "armory",
                                "localized_name": "armory"
                            },
                            "quality": {
                                "category": "quality",
                                "id": 516,
                                "internal_name": "normal",
                                "localized_name": "\u666e\u901a"
                            },
                            "rarity": {
                                "category": "rarity",
                                "id": 588,
                                "internal_name": "ancient_weapon",
                                "localized_name": "\u9690\u79d8"
                            },
                            "type": {
                                "category": "type",
                                "id": 570,
                                "internal_name": "csgo_type_rifle",
                                "localized_name": "\u6b65\u67aa"
                            },
                            "weapon": {
                                "category": "weapon",
                                "id": 533,
                                "internal_name": "weapon_m4a1_silencer",
                                "localized_name": "M4A1 \u6d88\u97f3\u7248"
                            },
                            "weaponcase": {
                                "category": "weaponcase",
                                "id": 19714,
                                "internal_name": "Gallery Case",
                                "localized_name": "gallery case"
                            }
                        }
                    },
                    "goods_id": 968376,
                    "localized_name": "M4A1 \u6d88\u97f3\u578b | \u84b8\u6c7d\u6ce2",
                    "max_price": "1538.35",
                    "min_price": "669"
                },
                {
                    "goods": {
                        "appid": 730,
                        "description": null,
                        "game": "csgo",
                        "goods_id": 968377,
                        "icon_url": "https://market.fp.ps.netease.com/file/66fe2b019ff9c7dee9de0d45AA0Yprws05",
                        "is_charm": false,
                        "item_id": null,
                        "keychain_color_img": null,
                        "market_hash_name": "Glock-18 | Gold Toof (Factory New)",
                        "market_min_price": "0",
                        "name": "\u683c\u6d1b\u514b 18 \u578b | \u5927\u91d1\u7259 (\u5d2d\u65b0\u51fa\u5382)",
                        "original_icon_url": "https://market.fp.ps.netease.com/file/66fe2afef518dbf73c79a733E8uhtNOK05",
                        "sell_min_price": "510",
                        "sell_reference_price": "0",
                        "short_name": "\u683c\u6d1b\u514b 18 \u578b | \u5927\u91d1\u7259",
                        "steam_price": "95.49",
                        "steam_price_cny": "690.8",
                        "tags": {
                            "category": {
                                "category": "category",
                                "id": 614,
                                "internal_name": "weapon_glock",
                                "localized_name": "\u683c\u6d1b\u514b 18 \u578b"
                            },
                            "category_group": {
                                "category": "category_group",
                                "id": 611,
                                "internal_name": "pistol",
                                "localized_name": "\u624b\u67aa"
                            },
                            "custom": {
                                "category": "custom",
                                "id": 11596,
                                "internal_name": "purple",
                                "localized_name": "purple"
                            },
                            "exterior": {
                                "category": "exterior",
                                "id": 510,
                                "internal_name": "wearcategory0",
                                "localized_name": "\u5d2d\u65b0\u51fa\u5382"
                            },
                            "itemset": {
                                "category": "itemset",
                                "id": 19715,
                                "internal_name": "armory",
                                "localized_name": "armory"
                            },
                            "quality": {
                                "category": "quality",
                                "id": 516,
                                "internal_name": "normal",
                                "localized_name": "\u666e\u901a"
                            },
                            "rarity": {
                                "category": "rarity",
                                "id": 588,
                                "internal_name": "ancient_weapon",
                                "localized_name": "\u9690\u79d8"
                            },
                            "type": {
                                "category": "type",
                                "id": 576,
                                "internal_name": "csgo_type_pistol",
                                "localized_name": "\u624b\u67aa"
                            },
                            "weapon": {
                                "category": "weapon",
                                "id": 531,
                                "internal_name": "weapon_glock",
                                "localized_name": "\u683c\u6d1b\u514b 18 \u578b"
                            },
                            "weaponcase": {
                                "category": "weaponcase",
                                "id": 19714,
                                "internal_name": "Gallery Case",
                                "localized_name": "gallery case"
                            }
                        }
                    },
                    "goods_id": 968377,
                    "localized_name": "\u683c\u6d1b\u514b 18 \u578b | \u5927\u91d1\u7259",
                    "max_price": "510",
                    "min_price": "103"
                },
                {
                    "goods": {
                        "appid": 730,
                        "description": null,
                        "game": "csgo",
                        "goods_id": 968205,
                        "icon_url": "https://market.fp.ps.netease.com/file/66fdf7bf0a3d243f6bd28c98AbiaBRNN05",
                        "is_charm": false,
                        "item_id": null,
                        "keychain_color_img": null,
                        "market_hash_name": "AK-47 | The Outsiders (Factory New)",
                        "market_min_price": "0",
                        "name": "AK-47 | \u5c40\u5916\u4eba (\u5d2d\u65b0\u51fa\u5382)",
                        "original_icon_url": "https://market.fp.ps.netease.com/file/66fdf7bdd907403efe01ac02QdfzwcZX05",
                        "sell_min_price": "713",
                        "sell_reference_price": "0",
                        "short_name": "AK-47 | \u5c40\u5916\u4eba",
                        "steam_price": "125",
                        "steam_price_cny": "904.28",
                        "tags": {
                            "category": {
                                "category": "category",
                                "id": 626,
                                "internal_name": "weapon_ak47",
                                "localized_name": "AK-47"
                            },
                            "category_group": {
                                "category": "category_group",
                                "id": 622,
                                "internal_name": "rifle",
                                "localized_name": "\u6b65\u67aa"
                            },
                            "custom": {
                                "category": "custom",
                                "id": 8788,
                                "internal_name": "green",
                                "localized_name": "green"
                            },
                            "exterior": {
                                "category": "exterior",
                                "id": 510,
                                "internal_name": "wearcategory0",
                                "localized_name": "\u5d2d\u65b0\u51fa\u5382"
                            },
                            "itemset": {
                                "category": "itemset",
                                "id": 19715,
                                "internal_name": "armory",
                                "localized_name": "armory"
                            },
                            "quality": {
                                "category": "quality",
                                "id": 516,
                                "internal_name": "normal",
                                "localized_name": "\u666e\u901a"
                            },
                            "rarity": {
                                "category": "rarity",
                                "id": 591,
                                "internal_name": "legendary_weapon",
                                "localized_name": "\u4fdd\u5bc6"
                            },
                            "type": {
                                "category": "type",
                                "id": 570,
                                "internal_name": "csgo_type_rifle",
                                "localized_name": "\u6b65\u67aa"
                            },
                            "weapon": {
                                "category": "weapon",
                                "id": 521,
                                "internal_name": "weapon_ak47",
                                "localized_name": "AK-47"
                            },
                            "weaponcase": {
                                "category": "weaponcase",
                                "id": 19714,
                                "internal_name": "Gallery Case",
                                "localized_name": "gallery case"
                            }
                        }
                    },
                    "goods_id": 968205,
                    "localized_name": "AK-47 | \u5c40\u5916\u4eba",
                    "max_price": "713",
                    "min_price": "77.9"
                },
                {
                    "goods": {
                        "appid": 730,
                        "description": null,
                        "game": "csgo",
                        "goods_id": 968058,
                        "icon_url": "https://market.fp.ps.netease.com/file/66fdf697e9981bec9286d84cf74iTsP405",
                        "is_charm": false,
                        "item_id": null,
                        "keychain_color_img": null,
                        "market_hash_name": "P250 | Epicenter (Factory New)",
                        "market_min_price": "0",
                        "name": "P250 | \u9707\u4e2d (\u5d2d\u65b0\u51fa\u5382)",
                        "original_icon_url": "https://market.fp.ps.netease.com/file/66fdf695d368fcd6cea3aab65qEZy7T105",
                        "sell_min_price": "126",
                        "sell_reference_price": "0",
                        "short_name": "P250 | \u9707\u4e2d",
                        "steam_price": "23",
                        "steam_price_cny": "166.39",
                        "tags": {
                            "category": {
                                "category": "category",
                                "id": 615,
                                "internal_name": "weapon_p250",
                                "localized_name": "P250"
                            },
                            "category_group": {
                                "category": "category_group",
                                "id": 611,
                                "internal_name": "pistol",
                                "localized_name": "\u624b\u67aa"
                            },
                            "custom": {
                                "category": "custom",
                                "id": 11596,
                                "internal_name": "purple",
                                "localized_name": "purple"
                            },
                            "exterior": {
                                "category": "exterior",
                                "id": 510,
                                "internal_name": "wearcategory0",
                                "localized_name": "\u5d2d\u65b0\u51fa\u5382"
                            },
                            "itemset": {
                                "category": "itemset",
                                "id": 19715,
                                "internal_name": "armory",
                                "localized_name": "armory"
                            },
                            "quality": {
                                "category": "quality",
                                "id": 516,
                                "internal_name": "normal",
                                "localized_name": "\u666e\u901a"
                            },
                            "rarity": {
                                "category": "rarity",
                                "id": 591,
                                "internal_name": "legendary_weapon",
                                "localized_name": "\u4fdd\u5bc6"
                            },
                            "type": {
                                "category": "type",
                                "id": 576,
                                "internal_name": "csgo_type_pistol",
                                "localized_name": "\u624b\u67aa"
                            },
                            "weapon": {
                                "category": "weapon",
                                "id": 542,
                                "internal_name": "weapon_p250",
                                "localized_name": "P250"
                            },
                            "weaponcase": {
                                "category": "weaponcase",
                                "id": 19714,
                                "internal_name": "Gallery Case",
                                "localized_name": "gallery case"
                            }
                        }
                    },
                    "goods_id": 968058,
                    "localized_name": "P250 | \u9707\u4e2d",
                    "max_price": "126",
                    "min_price": "51"
                },
                {
                    "goods": {
                        "appid": 730,
                        "description": null,
                        "game": "csgo",
                        "goods_id": 968401,
                        "icon_url": "https://market.fp.ps.netease.com/file/66fe05757ac4a065b5c11ef5oFD4ELEI05",
                        "is_charm": false,
                        "item_id": null,
                        "keychain_color_img": null,
                        "market_hash_name": "UMP-45 | Neo-Noir (Factory New)",
                        "market_min_price": "0",
                        "name": "UMP-45 | \u9ed1\u8272\u9b45\u5f71 (\u5d2d\u65b0\u51fa\u5382)",
                        "original_icon_url": "https://market.fp.ps.netease.com/file/66fe0573464aeb8ef53b846bVJIjO1lD05",
                        "sell_min_price": "128.88",
                        "sell_reference_price": "0",
                        "short_name": "UMP-45 | \u9ed1\u8272\u9b45\u5f71",
                        "steam_price": "27",
                        "steam_price_cny": "195.32",
                        "tags": {
                            "category": {
                                "category": "category",
                                "id": 637,
                                "internal_name": "weapon_ump45",
                                "localized_name": "UMP-45"
                            },
                            "category_group": {
                                "category": "category_group",
                                "id": 634,
                                "internal_name": "smg",
                                "localized_name": "\u5fae\u578b\u51b2\u950b\u67aa"
                            },
                            "custom": {
                                "category": "custom",
                                "id": 10774,
                                "internal_name": "Small_Neo-Noir",
                                "localized_name": "small_neo-noir"
                            },
                            "exterior": {
                                "category": "exterior",
                                "id": 510,
                                "internal_name": "wearcategory0",
                                "localized_name": "\u5d2d\u65b0\u51fa\u5382"
                            },
                            "itemset": {
                                "category": "itemset",
                                "id": 19715,
                                "internal_name": "armory",
                                "localized_name": "armory"
                            },
                            "quality": {
                                "category": "quality",
                                "id": 516,
                                "internal_name": "normal",
                                "localized_name": "\u666e\u901a"
                            },
                            "rarity": {
                                "category": "rarity",
                                "id": 591,
                                "internal_name": "legendary_weapon",
                                "localized_name": "\u4fdd\u5bc6"
                            },
                            "series": {
                                "category": "series",
                                "id": 10855,
                                "internal_name": "neo_noir",
                                "localized_name": "neo_noir"
                            },
                            "type": {
                                "category": "type",
                                "id": 578,
                                "internal_name": "csgo_type_smg",
                                "localized_name": "\u5fae\u578b\u51b2\u950b\u67aa"
                            },
                            "weapon": {
                                "category": "weapon",
                                "id": 551,
                                "internal_name": "weapon_ump45",
                                "localized_name": "UMP-45"
                            },
                            "weaponcase": {
                                "category": "weaponcase",
                                "id": 19714,
                                "internal_name": "Gallery Case",
                                "localized_name": "gallery case"
                            }
                        }
                    },
                    "goods_id": 968401,
                    "localized_name": "UMP-45 | \u9ed1\u8272\u9b45\u5f71",
                    "max_price": "128.88",
                    "min_price": "51.7"
                },
                {
                    "goods": {
                        "appid": 730,
                        "description": null,
                        "game": "csgo",
                        "goods_id": 968287,
                        "icon_url": "https://market.fp.ps.netease.com/file/66fe01627214a3fbd83c2f603ktxzes805",
                        "is_charm": false,
                        "item_id": null,
                        "keychain_color_img": null,
                        "market_hash_name": "M4A4 | Turbine (Factory New)",
                        "market_min_price": "0",
                        "name": "M4A4 | \u6da1\u8f6e (\u5d2d\u65b0\u51fa\u5382)",
                        "original_icon_url": "https://market.fp.ps.netease.com/file/66fe0160dafe01ed325849690hk1A0yo05",
                        "sell_min_price": "85.78",
                        "sell_reference_price": "0",
                        "short_name": "M4A4 | \u6da1\u8f6e",
                        "steam_price": "14.55",
                        "steam_price_cny": "105.26",
                        "tags": {
                            "category": {
                                "category": "category",
                                "id": 628,
                                "internal_name": "weapon_m4a1",
                                "localized_name": "M4A4"
                            },
                            "category_group": {
                                "category": "category_group",
                                "id": 622,
                                "internal_name": "rifle",
                                "localized_name": "\u6b65\u67aa"
                            },
                            "exterior": {
                                "category": "exterior",
                                "id": 510,
                                "internal_name": "wearcategory0",
                                "localized_name": "\u5d2d\u65b0\u51fa\u5382"
                            },
                            "itemset": {
                                "category": "itemset",
                                "id": 19715,
                                "internal_name": "armory",
                                "localized_name": "armory"
                            },
                            "quality": {
                                "category": "quality",
                                "id": 516,
                                "internal_name": "normal",
                                "localized_name": "\u666e\u901a"
                            },
                            "rarity": {
                                "category": "rarity",
                                "id": 590,
                                "internal_name": "mythical_weapon",
                                "localized_name": "\u53d7\u9650"
                            },
                            "type": {
                                "category": "type",
                                "id": 570,
                                "internal_name": "csgo_type_rifle",
                                "localized_name": "\u6b65\u67aa"
                            },
                            "weapon": {
                                "category": "weapon",
                                "id": 534,
                                "internal_name": "weapon_m4a1",
                                "localized_name": "M4A4"
                            },
                            "weaponcase": {
                                "category": "weaponcase",
                                "id": 19714,
                                "internal_name": "Gallery Case",
                                "localized_name": "gallery case"
                            }
                        }
                    },
                    "goods_id": 968287,
                    "localized_name": "M4A4 | \u6da1\u8f6e",
                    "max_price": "85.66",
                    "min_price": "6.99"
                },
                {
                    "goods": {
                        "appid": 730,
                        "description": null,
                        "game": "csgo",
                        "goods_id": 968034,
                        "icon_url": "https://market.fp.ps.netease.com/file/66fdf4bc983fac799424e89dBtxxmoVh05",
                        "is_charm": false,
                        "item_id": null,
                        "keychain_color_img": null,
                        "market_hash_name": "MAC-10 | Saib\u0101 Oni (Factory New)",
                        "market_min_price": "0",
                        "name": "MAC-10 | \u8d5b\u535a\u6076\u9b54 (\u5d2d\u65b0\u51fa\u5382)",
                        "original_icon_url": "https://market.fp.ps.netease.com/file/66fdf4ba95f26628296a9f51rBbZj6Mu05",
                        "sell_min_price": "36.98",
                        "sell_reference_price": "0",
                        "short_name": "MAC-10 | \u8d5b\u535a\u6076\u9b54",
                        "steam_price": "6.59",
                        "steam_price_cny": "47.67",
                        "tags": {
                            "category": {
                                "category": "category",
                                "id": 636,
                                "internal_name": "weapon_mac10",
                                "localized_name": "MAC-10"
                            },
                            "category_group": {
                                "category": "category_group",
                                "id": 634,
                                "internal_name": "smg",
                                "localized_name": "\u5fae\u578b\u51b2\u950b\u67aa"
                            },
                            "custom": {
                                "category": "custom",
                                "id": 11596,
                                "internal_name": "purple",
                                "localized_name": "purple"
                            },
                            "exterior": {
                                "category": "exterior",
                                "id": 510,
                                "internal_name": "wearcategory0",
                                "localized_name": "\u5d2d\u65b0\u51fa\u5382"
                            },
                            "itemset": {
                                "category": "itemset",
                                "id": 19715,
                                "internal_name": "armory",
                                "localized_name": "armory"
                            },
                            "quality": {
                                "category": "quality",
                                "id": 516,
                                "internal_name": "normal",
                                "localized_name": "\u666e\u901a"
                            },
                            "rarity": {
                                "category": "rarity",
                                "id": 590,
                                "internal_name": "mythical_weapon",
                                "localized_name": "\u53d7\u9650"
                            },
                            "type": {
                                "category": "type",
                                "id": 578,
                                "internal_name": "csgo_type_smg",
                                "localized_name": "\u5fae\u578b\u51b2\u950b\u67aa"
                            },
                            "weapon": {
                                "category": "weapon",
                                "id": 535,
                                "internal_name": "weapon_mac10",
                                "localized_name": "MAC-10"
                            },
                            "weaponcase": {
                                "category": "weaponcase",
                                "id": 19714,
                                "internal_name": "Gallery Case",
                                "localized_name": "gallery case"
                            }
                        }
                    },
                    "goods_id": 968034,
                    "localized_name": "MAC-10 | \u8d5b\u535a\u6076\u9b54",
                    "max_price": "37.2",
                    "min_price": "7.65"
                },
                {
                    "goods": {
                        "appid": 730,
                        "description": null,
                        "game": "csgo",
                        "goods_id": 968033,
                        "icon_url": "https://market.fp.ps.netease.com/file/66fdf20346c6950256284a97edPHb9UR05",
                        "is_charm": false,
                        "item_id": null,
                        "keychain_color_img": null,
                        "market_hash_name": "P90 | Randy Rush (Factory New)",
                        "market_min_price": "0",
                        "name": "P90 | \u5170\u8fea\u5feb\u51b2 (\u5d2d\u65b0\u51fa\u5382)",
                        "original_icon_url": "https://market.fp.ps.netease.com/file/66fdf201cd54e655cd706f31YgiQwAD105",
                        "sell_min_price": "37.6",
                        "sell_reference_price": "0",
                        "short_name": "P90 | \u5170\u8fea\u5feb\u51b2",
                        "steam_price": "6.64",
                        "steam_price_cny": "48.04",
                        "tags": {
                            "category": {
                                "category": "category",
                                "id": 635,
                                "internal_name": "weapon_p90",
                                "localized_name": "P90"
                            },
                            "category_group": {
                                "category": "category_group",
                                "id": 634,
                                "internal_name": "smg",
                                "localized_name": "\u5fae\u578b\u51b2\u950b\u67aa"
                            },
                            "exterior": {
                                "category": "exterior",
                                "id": 510,
                                "internal_name": "wearcategory0",
                                "localized_name": "\u5d2d\u65b0\u51fa\u5382"
                            },
                            "itemset": {
                                "category": "itemset",
                                "id": 19715,
                                "internal_name": "armory",
                                "localized_name": "armory"
                            },
                            "quality": {
                                "category": "quality",
                                "id": 516,
                                "internal_name": "normal",
                                "localized_name": "\u666e\u901a"
                            },
                            "rarity": {
                                "category": "rarity",
                                "id": 590,
                                "internal_name": "mythical_weapon",
                                "localized_name": "\u53d7\u9650"
                            },
                            "type": {
                                "category": "type",
                                "id": 578,
                                "internal_name": "csgo_type_smg",
                                "localized_name": "\u5fae\u578b\u51b2\u950b\u67aa"
                            },
                            "weapon": {
                                "category": "weapon",
                                "id": 543,
                                "internal_name": "weapon_p90",
                                "localized_name": "P90"
                            },
                            "weaponcase": {
                                "category": "weaponcase",
                                "id": 19714,
                                "internal_name": "Gallery Case",
                                "localized_name": "gallery case"
                            }
                        }
                    },
                    "goods_id": 968033,
                    "localized_name": "P90 | \u5170\u8fea\u5feb\u51b2",
                    "max_price": "37.6",
                    "min_price": "6.98"
                },
                {
                    "goods": {
                        "appid": 730,
                        "description": null,
                        "game": "csgo",
                        "goods_id": 968081,
                        "icon_url": "https://market.fp.ps.netease.com/file/66fde379fec5b439f9412cd8wB0kIlE305",
                        "is_charm": false,
                        "item_id": null,
                        "keychain_color_img": null,
                        "market_hash_name": "SSG 08 | Rapid Transit (Factory New)",
                        "market_min_price": "0",
                        "name": "SSG 08 | \u81f4\u547d\u7ad9\u70b9 (\u5d2d\u65b0\u51fa\u5382)",
                        "original_icon_url": "https://market.fp.ps.netease.com/file/66fde377034d04bb44561564rWxTKWla05",
                        "sell_min_price": "38.4",
                        "sell_reference_price": "0",
                        "short_name": "SSG 08 | \u81f4\u547d\u7ad9\u70b9",
                        "steam_price": "6.59",
                        "steam_price_cny": "47.67",
                        "tags": {
                            "category": {
                                "category": "category",
                                "id": 631,
                                "internal_name": "weapon_ssg08",
                                "localized_name": "SSG 08"
                            },
                            "category_group": {
                                "category": "category_group",
                                "id": 622,
                                "internal_name": "rifle",
                                "localized_name": "\u6b65\u67aa"
                            },
                            "custom": {
                                "category": "custom",
                                "id": 11595,
                                "internal_name": "white",
                                "localized_name": "white"
                            },
                            "exterior": {
                                "category": "exterior",
                                "id": 510,
                                "internal_name": "wearcategory0",
                                "localized_name": "\u5d2d\u65b0\u51fa\u5382"
                            },
                            "itemset": {
                                "category": "itemset",
                                "id": 19715,
                                "internal_name": "armory",
                                "localized_name": "armory"
                            },
                            "quality": {
                                "category": "quality",
                                "id": 516,
                                "internal_name": "normal",
                                "localized_name": "\u666e\u901a"
                            },
                            "rarity": {
                                "category": "rarity",
                                "id": 590,
                                "internal_name": "mythical_weapon",
                                "localized_name": "\u53d7\u9650"
                            },
                            "type": {
                                "category": "type",
                                "id": 571,
                                "internal_name": "csgo_type_sniperrifle",
                                "localized_name": "\u72d9\u51fb\u6b65\u67aa"
                            },
                            "weapon": {
                                "category": "weapon",
                                "id": 548,
                                "internal_name": "weapon_ssg08",
                                "localized_name": "SSG 08"
                            },
                            "weaponcase": {
                                "category": "weaponcase",
                                "id": 19714,
                                "internal_name": "Gallery Case",
                                "localized_name": "gallery case"
                            }
                        }
                    },
                    "goods_id": 968081,
                    "localized_name": "SSG 08 | \u81f4\u547d\u7ad9\u70b9",
                    "max_price": "38.5",
                    "min_price": "6.98"
                },
                {
                    "goods": {
                        "appid": 730,
                        "description": null,
                        "game": "csgo",
                        "goods_id": 968280,
                        "icon_url": "https://market.fp.ps.netease.com/file/66fe07c4a252666243647b80ycsgY6Pf05",
                        "is_charm": false,
                        "item_id": null,
                        "keychain_color_img": null,
                        "market_hash_name": "Dual Berettas | Hydro Strike (Factory New)",
                        "market_min_price": "0",
                        "name": "\u53cc\u6301\u8d1d\u745e\u5854 | \u6c34\u67aa\u51b2\u51fb (\u5d2d\u65b0\u51fa\u5382)",
                        "original_icon_url": "https://market.fp.ps.netease.com/file/66fe07c1cb622a1dd12d2d00KurPD4Rc05",
                        "sell_min_price": "38",
                        "sell_reference_price": "0",
                        "short_name": "\u53cc\u6301\u8d1d\u745e\u5854 | \u6c34\u67aa\u51b2\u51fb",
                        "steam_price": "6.52",
                        "steam_price_cny": "47.17",
                        "tags": {
                            "category": {
                                "category": "category",
                                "id": 621,
                                "internal_name": "weapon_elite",
                                "localized_name": "\u53cc\u6301\u8d1d\u745e\u5854"
                            },
                            "category_group": {
                                "category": "category_group",
                                "id": 611,
                                "internal_name": "pistol",
                                "localized_name": "\u624b\u67aa"
                            },
                            "custom": {
                                "category": "custom",
                                "id": 8785,
                                "internal_name": "blue",
                                "localized_name": "blue"
                            },
                            "exterior": {
                                "category": "exterior",
                                "id": 510,
                                "internal_name": "wearcategory0",
                                "localized_name": "\u5d2d\u65b0\u51fa\u5382"
                            },
                            "itemset": {
                                "category": "itemset",
                                "id": 19715,
                                "internal_name": "armory",
                                "localized_name": "armory"
                            },
                            "quality": {
                                "category": "quality",
                                "id": 516,
                                "internal_name": "normal",
                                "localized_name": "\u666e\u901a"
                            },
                            "rarity": {
                                "category": "rarity",
                                "id": 590,
                                "internal_name": "mythical_weapon",
                                "localized_name": "\u53d7\u9650"
                            },
                            "type": {
                                "category": "type",
                                "id": 576,
                                "internal_name": "csgo_type_pistol",
                                "localized_name": "\u624b\u67aa"
                            },
                            "weapon": {
                                "category": "weapon",
                                "id": 526,
                                "internal_name": "weapon_elite",
                                "localized_name": "\u53cc\u6301\u8d1d\u745e\u5854"
                            },
                            "weaponcase": {
                                "category": "weaponcase",
                                "id": 19714,
                                "internal_name": "Gallery Case",
                                "localized_name": "gallery case"
                            }
                        }
                    },
                    "goods_id": 968280,
                    "localized_name": "\u53cc\u6301\u8d1d\u745e\u5854 | \u6c34\u67aa\u51b2\u51fb",
                    "max_price": "37.99",
                    "min_price": "6.97"
                },
                {
                    "goods": {
                        "appid": 730,
                        "description": null,
                        "game": "csgo",
                        "goods_id": 968209,
                        "icon_url": "https://market.fp.ps.netease.com/file/66fdfc6bb28689d4534d3d37zJSbgGVZ05",
                        "is_charm": false,
                        "item_id": null,
                        "keychain_color_img": null,
                        "market_hash_name": "AUG | Luxe Trim (Factory New)",
                        "market_min_price": "0",
                        "name": "AUG | \u8c6a\u534e\u88c5\u9970 (\u5d2d\u65b0\u51fa\u5382)",
                        "original_icon_url": "https://market.fp.ps.netease.com/file/66fdfc6929508793fdc424ebJL0rJ8ZB05",
                        "sell_min_price": "6.12",
                        "sell_reference_price": "0",
                        "short_name": "AUG | \u8c6a\u534e\u88c5\u9970",
                        "steam_price": "1.04",
                        "steam_price_cny": "7.52",
                        "tags": {
                            "category": {
                                "category": "category",
                                "id": 632,
                                "internal_name": "weapon_aug",
                                "localized_name": "AUG"
                            },
                            "category_group": {
                                "category": "category_group",
                                "id": 622,
                                "internal_name": "rifle",
                                "localized_name": "\u6b65\u67aa"
                            },
                            "custom": {
                                "category": "custom",
                                "id": 8791,
                                "internal_name": "black",
                                "localized_name": "black"
                            },
                            "exterior": {
                                "category": "exterior",
                                "id": 510,
                                "internal_name": "wearcategory0",
                                "localized_name": "\u5d2d\u65b0\u51fa\u5382"
                            },
                            "itemset": {
                                "category": "itemset",
                                "id": 19715,
                                "internal_name": "armory",
                                "localized_name": "armory"
                            },
                            "quality": {
                                "category": "quality",
                                "id": 516,
                                "internal_name": "normal",
                                "localized_name": "\u666e\u901a"
                            },
                            "rarity": {
                                "category": "rarity",
                                "id": 589,
                                "internal_name": "rare_weapon",
                                "localized_name": "\u519b\u89c4\u7ea7"
                            },
                            "type": {
                                "category": "type",
                                "id": 570,
                                "internal_name": "csgo_type_rifle",
                                "localized_name": "\u6b65\u67aa"
                            },
                            "weapon": {
                                "category": "weapon",
                                "id": 522,
                                "internal_name": "weapon_aug",
                                "localized_name": "AUG"
                            },
                            "weaponcase": {
                                "category": "weaponcase",
                                "id": 19714,
                                "internal_name": "Gallery Case",
                                "localized_name": "gallery case"
                            }
                        }
                    },
                    "goods_id": 968209,
                    "localized_name": "AUG | \u8c6a\u534e\u88c5\u9970",
                    "max_price": "6.12",
                    "min_price": "0.83"
                },
                {
                    "goods": {
                        "appid": 730,
                        "description": null,
                        "game": "csgo",
                        "goods_id": 968333,
                        "icon_url": "https://market.fp.ps.netease.com/file/66fde9c25cf3f7f40fa1bcbdiDjz5OG305",
                        "is_charm": false,
                        "item_id": null,
                        "keychain_color_img": null,
                        "market_hash_name": "M249 | Hypnosis (Factory New)",
                        "market_min_price": "0",
                        "name": "M249 | \u50ac\u7720\u672f (\u5d2d\u65b0\u51fa\u5382)",
                        "original_icon_url": "https://market.fp.ps.netease.com/file/66fde9bfccefee2f46865754vi3PfaaY05",
                        "sell_min_price": "5.86",
                        "sell_reference_price": "0",
                        "short_name": "M249 | \u50ac\u7720\u672f",
                        "steam_price": "0.96",
                        "steam_price_cny": "6.94",
                        "tags": {
                            "category": {
                                "category": "category",
                                "id": 647,
                                "internal_name": "weapon_m249",
                                "localized_name": "M249"
                            },
                            "category_group": {
                                "category": "category_group",
                                "id": 646,
                                "internal_name": "machinegun",
                                "localized_name": "\u673a\u67aa"
                            },
                            "custom": {
                                "category": "custom",
                                "id": 8785,
                                "internal_name": "blue",
                                "localized_name": "blue"
                            },
                            "exterior": {
                                "category": "exterior",
                                "id": 510,
                                "internal_name": "wearcategory0",
                                "localized_name": "\u5d2d\u65b0\u51fa\u5382"
                            },
                            "itemset": {
                                "category": "itemset",
                                "id": 19715,
                                "internal_name": "armory",
                                "localized_name": "armory"
                            },
                            "quality": {
                                "category": "quality",
                                "id": 516,
                                "internal_name": "normal",
                                "localized_name": "\u666e\u901a"
                            },
                            "rarity": {
                                "category": "rarity",
                                "id": 589,
                                "internal_name": "rare_weapon",
                                "localized_name": "\u519b\u89c4\u7ea7"
                            },
                            "type": {
                                "category": "type",
                                "id": 577,
                                "internal_name": "csgo_type_machinegun",
                                "localized_name": "\u673a\u67aa"
                            },
                            "weapon": {
                                "category": "weapon",
                                "id": 532,
                                "internal_name": "weapon_m249",
                                "localized_name": "M249"
                            },
                            "weaponcase": {
                                "category": "weaponcase",
                                "id": 19714,
                                "internal_name": "Gallery Case",
                                "localized_name": "gallery case"
                            }
                        }
                    },
                    "goods_id": 968333,
                    "localized_name": "M249 | \u50ac\u7720\u672f",
                    "max_price": "5.86",
                    "min_price": "0.75"
                },
                {
                    "goods": {
                        "appid": 730,
                        "description": null,
                        "game": "csgo",
                        "goods_id": 968085,
                        "icon_url": "https://market.fp.ps.netease.com/file/66fdeed61d06a820163b65c0s74FIiKM05",
                        "is_charm": false,
                        "item_id": null,
                        "keychain_color_img": null,
                        "market_hash_name": "MP5-SD | Statics (Factory New)",
                        "market_min_price": "0",
                        "name": "MP5-SD | \u9759\u6001\u5b66 (\u5d2d\u65b0\u51fa\u5382)",
                        "original_icon_url": "https://market.fp.ps.netease.com/file/66fdeed5bcf0c841fc571100kQ5ix9lD05",
                        "sell_min_price": "6.26",
                        "sell_reference_price": "0",
                        "short_name": "MP5-SD | \u9759\u6001\u5b66",
                        "steam_price": "1.07",
                        "steam_price_cny": "7.74",
                        "tags": {
                            "category": {
                                "category": "category",
                                "id": 714,
                                "internal_name": "weapon_mp5sd",
                                "localized_name": "MP5-SD"
                            },
                            "category_group": {
                                "category": "category_group",
                                "id": 634,
                                "internal_name": "smg",
                                "localized_name": "\u5fae\u578b\u51b2\u950b\u67aa"
                            },
                            "custom": {
                                "category": "custom",
                                "id": 8785,
                                "internal_name": "blue",
                                "localized_name": "blue"
                            },
                            "exterior": {
                                "category": "exterior",
                                "id": 510,
                                "internal_name": "wearcategory0",
                                "localized_name": "\u5d2d\u65b0\u51fa\u5382"
                            },
                            "itemset": {
                                "category": "itemset",
                                "id": 19715,
                                "internal_name": "armory",
                                "localized_name": "armory"
                            },
                            "quality": {
                                "category": "quality",
                                "id": 516,
                                "internal_name": "normal",
                                "localized_name": "\u666e\u901a"
                            },
                            "rarity": {
                                "category": "rarity",
                                "id": 589,
                                "internal_name": "rare_weapon",
                                "localized_name": "\u519b\u89c4\u7ea7"
                            },
                            "type": {
                                "category": "type",
                                "id": 578,
                                "internal_name": "csgo_type_smg",
                                "localized_name": "\u5fae\u578b\u51b2\u950b\u67aa"
                            },
                            "weapon": {
                                "category": "weapon",
                                "internal_name": "weapon_mp5sd",
                                "localized_name": "MP5-SD"
                            },
                            "weaponcase": {
                                "category": "weaponcase",
                                "id": 19714,
                                "internal_name": "Gallery Case",
                                "localized_name": "gallery case"
                            }
                        }
                    },
                    "goods_id": 968085,
                    "localized_name": "MP5-SD | \u9759\u6001\u5b66",
                    "max_price": "6.26",
                    "min_price": "0.77"
                },
                {
                    "goods": {
                        "appid": 730,
                        "description": null,
                        "game": "csgo",
                        "goods_id": 968315,
                        "icon_url": "https://market.fp.ps.netease.com/file/66fdfb30a46990b5e475cf92FNdH0HQk05",
                        "is_charm": false,
                        "item_id": null,
                        "keychain_color_img": null,
                        "market_hash_name": "R8 Revolver | Tango (Factory New)",
                        "market_min_price": "0",
                        "name": "R8 \u5de6\u8f6e\u624b\u67aa | \u63a2\u6208 (\u5d2d\u65b0\u51fa\u5382)",
                        "original_icon_url": "https://market.fp.ps.netease.com/file/66fdfb2ed0704f1e2e22f8936Fmj1Ltk05",
                        "sell_min_price": "6.57",
                        "sell_reference_price": "0",
                        "short_name": "R8 \u5de6\u8f6e\u624b\u67aa | \u63a2\u6208",
                        "steam_price": "1",
                        "steam_price_cny": "7.23",
                        "tags": {
                            "category": {
                                "category": "category",
                                "id": 619,
                                "internal_name": "weapon_revolver",
                                "localized_name": "R8 \u5de6\u8f6e\u624b\u67aa"
                            },
                            "category_group": {
                                "category": "category_group",
                                "id": 611,
                                "internal_name": "pistol",
                                "localized_name": "\u624b\u67aa"
                            },
                            "exterior": {
                                "category": "exterior",
                                "id": 510,
                                "internal_name": "wearcategory0",
                                "localized_name": "\u5d2d\u65b0\u51fa\u5382"
                            },
                            "itemset": {
                                "category": "itemset",
                                "id": 19715,
                                "internal_name": "armory",
                                "localized_name": "armory"
                            },
                            "quality": {
                                "category": "quality",
                                "id": 516,
                                "internal_name": "normal",
                                "localized_name": "\u666e\u901a"
                            },
                            "rarity": {
                                "category": "rarity",
                                "id": 589,
                                "internal_name": "rare_weapon",
                                "localized_name": "\u519b\u89c4\u7ea7"
                            },
                            "type": {
                                "category": "type",
                                "id": 576,
                                "internal_name": "csgo_type_pistol",
                                "localized_name": "\u624b\u67aa"
                            },
                            "weapon": {
                                "category": "weapon",
                                "id": 545,
                                "internal_name": "weapon_revolver",
                                "localized_name": "R8 \u5de6\u8f6e\u624b\u67aa"
                            },
                            "weaponcase": {
                                "category": "weaponcase",
                                "id": 19714,
                                "internal_name": "Gallery Case",
                                "localized_name": "gallery case"
                            }
                        }
                    },
                    "goods_id": 968315,
                    "localized_name": "R8 \u5de6\u8f6e\u624b\u67aa | \u63a2\u6208",
                    "max_price": "6.57",
                    "min_price": "0.77"
                },
                {
                    "goods": {
                        "appid": 730,
                        "description": null,
                        "game": "csgo",
                        "goods_id": 968108,
                        "icon_url": "https://market.fp.ps.netease.com/file/66fde850959cba1260a398b0qa6K02jR05",
                        "is_charm": false,
                        "item_id": null,
                        "keychain_color_img": null,
                        "market_hash_name": "SCAR-20 | Trail Blazer (Factory New)",
                        "market_min_price": "0",
                        "name": "SCAR-20 | \u5f00\u62d3\u8005 (\u5d2d\u65b0\u51fa\u5382)",
                        "original_icon_url": "https://market.fp.ps.netease.com/file/66fde84def80ebf67b456bfa9VYs7MFj05",
                        "sell_min_price": "5.15",
                        "sell_reference_price": "0",
                        "short_name": "SCAR-20 | \u5f00\u62d3\u8005",
                        "steam_price": "0.87",
                        "steam_price_cny": "6.29",
                        "tags": {
                            "category": {
                                "category": "category",
                                "id": 624,
                                "internal_name": "weapon_scar20",
                                "localized_name": "SCAR-20"
                            },
                            "category_group": {
                                "category": "category_group",
                                "id": 622,
                                "internal_name": "rifle",
                                "localized_name": "\u6b65\u67aa"
                            },
                            "custom": {
                                "category": "custom",
                                "id": 8791,
                                "internal_name": "black",
                                "localized_name": "black"
                            },
                            "exterior": {
                                "category": "exterior",
                                "id": 510,
                                "internal_name": "wearcategory0",
                                "localized_name": "\u5d2d\u65b0\u51fa\u5382"
                            },
                            "itemset": {
                                "category": "itemset",
                                "id": 19715,
                                "internal_name": "armory",
                                "localized_name": "armory"
                            },
                            "quality": {
                                "category": "quality",
                                "id": 516,
                                "internal_name": "normal",
                                "localized_name": "\u666e\u901a"
                            },
                            "rarity": {
                                "category": "rarity",
                                "id": 589,
                                "internal_name": "rare_weapon",
                                "localized_name": "\u519b\u89c4\u7ea7"
                            },
                            "type": {
                                "category": "type",
                                "id": 571,
                                "internal_name": "csgo_type_sniperrifle",
                                "localized_name": "\u72d9\u51fb\u6b65\u67aa"
                            },
                            "weapon": {
                                "category": "weapon",
                                "id": 546,
                                "internal_name": "weapon_scar20",
                                "localized_name": "SCAR-20"
                            },
                            "weaponcase": {
                                "category": "weaponcase",
                                "id": 19714,
                                "internal_name": "Gallery Case",
                                "localized_name": "gallery case"
                            }
                        }
                    },
                    "goods_id": 968108,
                    "localized_name": "SCAR-20 | \u5f00\u62d3\u8005",
                    "max_price": "5.15",
                    "min_price": "0.76"
                },
                {
                    "goods": {
                        "appid": 730,
                        "description": null,
                        "game": "csgo",
                        "goods_id": 968089,
                        "icon_url": "https://market.fp.ps.netease.com/file/66fded9df9539063d28cc7c0L9kCUTr605",
                        "is_charm": false,
                        "item_id": null,
                        "keychain_color_img": null,
                        "market_hash_name": "USP-S | 27 (Factory New)",
                        "market_min_price": "0",
                        "name": "USP \u6d88\u97f3\u7248 | 27 (\u5d2d\u65b0\u51fa\u5382)",
                        "original_icon_url": "https://market.fp.ps.netease.com/file/66fded9b3df285841ad6c6557l3HfsZs05",
                        "sell_min_price": "6.1",
                        "sell_reference_price": "0",
                        "short_name": "USP \u6d88\u97f3\u7248 | 27",
                        "steam_price": "1.22",
                        "steam_price_cny": "8.83",
                        "tags": {
                            "category": {
                                "category": "category",
                                "id": 613,
                                "internal_name": "weapon_usp_silencer",
                                "localized_name": "USP \u6d88\u97f3\u7248"
                            },
                            "category_group": {
                                "category": "category_group",
                                "id": 611,
                                "internal_name": "pistol",
                                "localized_name": "\u624b\u67aa"
                            },
                            "exterior": {
                                "category": "exterior",
                                "id": 510,
                                "internal_name": "wearcategory0",
                                "localized_name": "\u5d2d\u65b0\u51fa\u5382"
                            },
                            "itemset": {
                                "category": "itemset",
                                "id": 19715,
                                "internal_name": "armory",
                                "localized_name": "armory"
                            },
                            "quality": {
                                "category": "quality",
                                "id": 516,
                                "internal_name": "normal",
                                "localized_name": "\u666e\u901a"
                            },
                            "rarity": {
                                "category": "rarity",
                                "id": 589,
                                "internal_name": "rare_weapon",
                                "localized_name": "\u519b\u89c4\u7ea7"
                            },
                            "type": {
                                "category": "type",
                                "id": 576,
                                "internal_name": "csgo_type_pistol",
                                "localized_name": "\u624b\u67aa"
                            },
                            "weapon": {
                                "category": "weapon",
                                "id": 552,
                                "internal_name": "weapon_usp_silencer",
                                "localized_name": "USP \u6d88\u97f3\u7248"
                            },
                            "weaponcase": {
                                "category": "weaponcase",
                                "id": 19714,
                                "internal_name": "Gallery Case",
                                "localized_name": "gallery case"
                            }
                        }
                    },
                    "goods_id": 968089,
                    "localized_name": "USP \u6d88\u97f3\u7248 | 27",
                    "max_price": "6.09",
                    "min_price": "0.86"
                },
                {
                    "goods": {
                        "appid": 730,
                        "description": null,
                        "game": "csgo",
                        "goods_id": 968181,
                        "icon_url": "https://market.fp.ps.netease.com/file/66fdf166d01c9bd8a7990963CZOvhJ0K05",
                        "is_charm": false,
                        "item_id": null,
                        "keychain_color_img": null,
                        "market_hash_name": "Desert Eagle | Calligraffiti (Factory New)",
                        "market_min_price": "0",
                        "name": "\u6c99\u6f20\u4e4b\u9e70 | \u4e66\u6cd5\u6d82\u9e26 (\u5d2d\u65b0\u51fa\u5382)",
                        "original_icon_url": "https://market.fp.ps.netease.com/file/66fdf1649db810c5c5a6d122isbS2iMK05",
                        "sell_min_price": "6.13",
                        "sell_reference_price": "0",
                        "short_name": "\u6c99\u6f20\u4e4b\u9e70 | \u4e66\u6cd5\u6d82\u9e26",
                        "steam_price": "1.21",
                        "steam_price_cny": "8.75",
                        "tags": {
                            "category": {
                                "category": "category",
                                "id": 620,
                                "internal_name": "weapon_deagle",
                                "localized_name": "\u6c99\u6f20\u4e4b\u9e70"
                            },
                            "category_group": {
                                "category": "category_group",
                                "id": 611,
                                "internal_name": "pistol",
                                "localized_name": "\u624b\u67aa"
                            },
                            "exterior": {
                                "category": "exterior",
                                "id": 510,
                                "internal_name": "wearcategory0",
                                "localized_name": "\u5d2d\u65b0\u51fa\u5382"
                            },
                            "itemset": {
                                "category": "itemset",
                                "id": 19715,
                                "internal_name": "armory",
                                "localized_name": "armory"
                            },
                            "quality": {
                                "category": "quality",
                                "id": 516,
                                "internal_name": "normal",
                                "localized_name": "\u666e\u901a"
                            },
                            "rarity": {
                                "category": "rarity",
                                "id": 589,
                                "internal_name": "rare_weapon",
                                "localized_name": "\u519b\u89c4\u7ea7"
                            },
                            "type": {
                                "category": "type",
                                "id": 576,
                                "internal_name": "csgo_type_pistol",
                                "localized_name": "\u624b\u67aa"
                            },
                            "weapon": {
                                "category": "weapon",
                                "id": 525,
                                "internal_name": "weapon_deagle",
                                "localized_name": "\u6c99\u6f20\u4e4b\u9e70"
                            },
                            "weaponcase": {
                                "category": "weaponcase",
                                "id": 19714,
                                "internal_name": "Gallery Case",
                                "localized_name": "gallery case"
                            }
                        }
                    },
                    "goods_id": 968181,
                    "localized_name": "\u6c99\u6f20\u4e4b\u9e70 | \u4e66\u6cd5\u6d82\u9e26",
                    "max_price": "6.13",
                    "min_price": "0.77"
                }
            ]
        },
        "msg": null
    }
]